<annotation>
	<folder>queen_hearts</folder>
	<filename>CK_queen_hearts27.jpg</filename>
	<path>/Users/chelseakuball/labelImg/queen_hearts/CK_queen_hearts27.jpg</path>
	<source>
		<database>Unknown</database>
	</source>
	<size>
		<width>300</width>
		<height>300</height>
		<depth>3</depth>
	</size>
	<segmented>0</segmented>
	<object>
		<name>QueenOfHearts</name>
		<pose>Unspecified</pose>
		<truncated>0</truncated>
		<difficult>0</difficult>
		<bndbox>
			<xmin>125</xmin>
			<ymin>29</ymin>
			<xmax>197</xmax>
			<ymax>95</ymax>
		</bndbox>
	</object>
	<object>
		<name>KingOfSpades</name>
		<pose>Unspecified</pose>
		<truncated>0</truncated>
		<difficult>0</difficult>
		<bndbox>
			<xmin>190</xmin>
			<ymin>46</ymin>
			<xmax>296</xmax>
			<ymax>232</ymax>
		</bndbox>
	</object>
	<object>
		<name>JackOfClubs</name>
		<pose>Unspecified</pose>
		<truncated>0</truncated>
		<difficult>0</difficult>
		<bndbox>
			<xmin>56</xmin>
			<ymin>41</ymin>
			<xmax>133</xmax>
			<ymax>180</ymax>
		</bndbox>
	</object>
	<object>
		<name>KingOfDiamonds</name>
		<pose>Unspecified</pose>
		<truncated>1</truncated>
		<difficult>0</difficult>
		<bndbox>
			<xmin>1</xmin>
			<ymin>72</ymin>
			<xmax>76</xmax>
			<ymax>199</ymax>
		</bndbox>
	</object>
</annotation>
