<annotation>
	<folder>QueenOfHearts</folder>
	<filename>DV_QueenOfHearts_(8).JPG</filename>
	<path>/var/host/media/removable/USB20FD/images//var/host/media/removable/USB20FD/annotations/DV_QueenOfHearts_(8).xml</path>
	<source>
		<database>Unknown</database>
	</source>
	<size>
		<width>320</width>
		<height>240</height>
		<depth>3</depth>
	</size>
	<segmented>0</segmented>
	<object>
		<name>QueenOfHearts</name>
		<pose>Unspecified</pose>
		<truncated>0</truncated>
		<difficult>0</difficult>
		<bndbox>
			<xmin>157</xmin>
			<ymin>10</ymin>
			<xmax>229</xmax>
			<ymax>95</ymax>
		</bndbox>
	</object>
</annotation>