<annotation>
  <folder>KingOfDiamonds</folder>
  <filename>KingOfDiamonds_11.jpg</filename>
  <path>C:\Users\Adam\Dropbox\Public\images\KingOfDiamonds\KingOfDiamonds_11.jpg</path>
  <source>
    <database>Unknown</database>
  </source>
  <size>
    <width>300</width>
    <height>225</height>
    <depth>3</depth>
  </size>
  <segmented>0</segmented>
  <object>
    <name>KingOfDiamonds</name>
    <pose>Unspecified</pose>
    <truncated>0</truncated>
    <difficult>0</difficult>
    <bndbox>
      <xmin>14</xmin>
      <ymin>189</ymin>
      <xmax>114</xmax>
      <ymax>225</ymax>
    </bndbox>
  </object>
</annotation>
