<annotation>
	<folder>KingOfSpades</folder>
	<filename>RS_KingOfSpades_(33).jpg</filename>
	<path>C:\Users\Rupal Shah\Dropbox\!!! Week 5\KingOfSpades\RS_KingOfSpades_(33).jpg</path>
	<source>
		<database>Unknown</database>
	</source>
	<size>
		<width>320</width>
		<height>240</height>
		<depth>3</depth>
	</size>
	<segmented>0</segmented>
	<object>
		<name>KingOfSpades</name>
		<pose>Unspecified</pose>
		<truncated>0</truncated>
		<difficult>0</difficult>
		<bndbox>
			<xmin>8</xmin>
			<ymin>19</ymin>
			<xmax>121</xmax>
			<ymax>175</ymax>
		</bndbox>
	</object>
</annotation>
