<annotation verified="yes">
	<folder>Queen of Hearts</folder>
	<filename>RS_QueenofHearts_(47).jpg</filename>
	<path>/var/host/media/removable/USB20FD/images//var/host/media/removable/USB20FD/annotations/RS_QueenofHearts_(47).xml</path>
	<source>
		<database>Unknown</database>
	</source>
	<size>
		<width>4032</width>
		<height>3024</height>
		<depth>3</depth>
	</size>
	<segmented>0</segmented>
	<object>
		<name>QueenOfHearts</name>
		<pose>Unspecified</pose>
		<truncated>0</truncated>
		<difficult>0</difficult>
		<bndbox>
			<xmin>2073</xmin>
			<ymin>1186</ymin>
			<xmax>2987</xmax>
			<ymax>1850</ymax>
		</bndbox>
	</object>
</annotation>